<?xml version="1.0" encoding="UTF-8"?>
<!--
 Copyright (c) 2015 CableLabs, Inc. and others.  All rights reserved.

 This program and the accompanying materials are made available under the
 terms of the Eclipse Public License v1.0 which accompanies this distribution,
 and is available at http://www.eclipse.org/legal/epl-v10.html
-->
<features name="odl-packetcable-${project.version}" xmlns="http://karaf.apache.org/xmlns/features/v1.2.0"
    xmlns:xsi="http://www.w3.org/2001/XMLSchema-instance"
    xsi:schemaLocation="http://karaf.apache.org/xmlns/features/v1.2.0 http://karaf.apache.org/xmlns/features/v1.2.0">
    <repository>mvn:org.opendaylight.yangtools/features-yangtools/${yangtools.version}/xml/features</repository>
    <repository>mvn:org.opendaylight.controller/features-mdsal/${mdsal.version}/xml/features</repository>
    <repository>mvn:org.opendaylight.controller/features-restconf/${mdsal.version}/xml/features</repository>
    <feature name='odl-packetcable-policy-server-all' version='${project.version}'
        description='OpenDaylight :: packetcable :: policy :: All'>
        <feature version='${project.version}'>odl-packetcable-policy-server</feature>
    </feature>
    <feature name='odl-packetcable-policy-model' version='${project.version}'
        description='OpenDaylight :: packetcable :: policy :: Model'>
        <feature version='${yangtools.version}'>odl-mdsal-binding-base</feature>
        <feature version='${yangtools.version}'>odl-mdsal-models</feature>
        <bundle>mvn:org.opendaylight.packetcable/packetcable-policy-model/${project.version}</bundle>
    </feature>
    <feature name='odl-packetcable-policy-server' version='${project.version}'
        description='OpenDaylight :: packetcable :: policy :: Provider'>
        <feature version='${mdsal.version}'>odl-mdsal-broker</feature>
        <feature version="${mdsal.version}">odl-mdsal-apidocs</feature>
        <feature version='${project.version}'>odl-packetcable-policy-model</feature>
        <bundle>mvn:org.opendaylight.packetcable/packetcable-policy-server/${project.version}</bundle>
        <bundle>mvn:org.opendaylight.packetcable/packetcable-driver/${project.version}</bundle>
        <configfile finalname="etc/opendaylight/karaf/80-packetcable.xml">mvn:org.opendaylight.packetcable/packetcable-policy-server/${project.version}/xml/config</configfile>
    </feature>
</features>